cartrackerreader/__init__.py
cartrackerreader/__main__.py
cartrackerreader-1.0.1.dist-info/LICENSE.txt
cartrackerreader-1.0.1.dist-info/METADATA
cartrackerreader-1.0.1.dist-info/WHEEL
cartrackerreader-1.0.1.dist-info/entry_points.txt
cartrackerreader-1.0.1.dist-info/top_level.txt
cartrackerreader-1.0.1.dist-info/RECORD
