Metadata-Version: 2.1
Name: cartrackerreader
Version: 1.0.1
Summary: Python app for reading the storage of the car tracker via USB serial port
Home-page: https://github.com/Grvs44/cartrackerreader
Author: Joe Greaves
Classifier: License :: OSI Approved :: BSD License
Classifier: Programming Language :: Python :: 3
Classifier: Programming Language :: Python :: 3.9
Classifier: Programming Language :: Python :: 3.10
Classifier: Programming Language :: Python :: 3 :: Only
Requires-Python: >=3.9, <4
License-File: LICENSE.txt
Requires-Dist: pyserial
